{
  "formatVersion": 0,
  "id": "1.14.3+build.1",
  "releaseType": "beta",
  "side": "universal",
  "relationships": [
    {
      "type": "required",
      "id": "com.mojang.minecraft",
      "version": "1.14.3",
      "side": "universal"
    }
  ],
  "artifacts": [
    {
      "type": "maven",
      "id": "net.fabricmc:yarn:1.14.3+build.1",
      "side": "universal"
    },
    {
      "type": "direct",
      "id": "https://maven.fabricmc.net/net/fabricmc/yarn/1.14.3+build.1/yarn-1.14.3+build.1.jar",
      "side": "universal"
    }
  ],
  "hashes": {
    "sha1": "03db732395d5c9e05f25aa57180dc83c1d3540de",
    "md5": "9c1873ae1efc55344b81b0256653cd9d"
  },
  "size": 503467,
  "releaseTime": "2019-06-24T15:09:47Z"
}