{
  "formatVersion": 0,
  "id": "0.2.0.54",
  "releaseType": "beta",
  "changelog": "",
  "side": "universal",
  "relationships": [
    {
      "type": "required",
      "id": "yarn",
      "version": "*"
    }
  ],
  "artifacts": [
    {
      "type": "maven",
      "id": "net.fabricmc:fabric-loader:0.2.0.54"
    },
    {
      "type": "direct",
      "id": "https://maven.fabricmc.net/net/fabricmc/fabric-loader/0.2.0.54/fabric-loader-0.2.0.54.jar"
    }
  ],
  "hashes": {
    "sha1": "0a2dc74fc9a6afb58a14cfe44ee30c37008a12ea",
    "md5": "890019c9e14c2ef1cc07e10a3f160959"
  },
  "size": 68805,
  "filename": "",
  "releaseTime": "2018-12-09T16:59:57Z"
}