{
  "formatVersion": 0,
  "id": "2.1.4.43",
  "releaseType": "release",
  "changelog": "https://www.curseforge.com/minecraft/mc-mods/mrtjpcore/files/2735197",
  "side": "universal",
  "artifacts": [
    {
      "type": "direct",
      "id": "https://edge.forgecdn.net/files/2735/197/MrTJPCore-1.12.2-2.1.4.43-universal.jar",
      "side": "universal"
    }
  ],
  "hashes": {
    "sha1": "da39a3ee5e6b4b0d3255bfef95601890afd80709",
    "sha256": "e3b0c44298fc1c149afbf4c8996fb92427ae41e4649b934ca495991b7852b855",
    "murmur2": "4068050300",
    "md5": "edff42a77c41f9191722b5b794e37668"
  },
  "size": 803400,
  "releaseTime": "2019-07-04T00:12:13.943Z"
}