{
  "formatVersion": 0,
  "id": "rv5-alpha-1",
  "releaseType": "release",
  "changelog": "",
  "side": "universal",
  "relationships": [
    {
      "type": "required",
      "id": "minecraft",
      "version": "1.12"
    }
  ],
  "artifacts": [
    {
      "type": "curseforge",
      "id": "2457650"
    },
    {
      "type": "direct",
      "id": "https://files.forgecdn.net/files/2457/650/appliedenergistics2-rv5-alpha-1.jar"
    }
  ],
  "hashes": {},
  "size": 0,
  "filename": "",
  "releaseTime": ""
}